pipStudy/__init__.py
pipStudy/util.py
pipStudy001-0.0.3.dist-info/METADATA
pipStudy001-0.0.3.dist-info/WHEEL
pipStudy001-0.0.3.dist-info/top_level.txt
pipStudy001-0.0.3.dist-info/RECORD
