Metadata-Version: 2.1
Name: pipStudy001
Version: 0.0.3
Summary: pip test functions
Home-page: UNKNOWN
Author: fdd
Author-email: 1316017498@qq.com
License: apache 3.0
Platform: UNKNOWN
Requires: json
Requires: requests
